LICENSE
README.md
setup.cfg
setup.py
muCART/__init__.py
muCART/grid_search.py
muCART/mu_cart.py
muCART/mu_node.py
muCART.egg-info/PKG-INFO
muCART.egg-info/SOURCES.txt
muCART.egg-info/dependency_links.txt
muCART.egg-info/requires.txt
muCART.egg-info/top_level.txt