Metadata-Version: 2.1
Name: muCART
Version: 1.0.2
Summary: Measure Inducing Classification and Regression Trees
Home-page: https://github.com/bellibot/muCART
Author: Edoardo Belli
Author-email: iedobelli@gmail.com
License: MIT
Download-URL: https://github.com/bellibot/muCART/archive/refs/tags/v1.0.1.tar.gz
Keywords: Decision Tree,Functional Data,Classification,Regression
Platform: UNKNOWN
Classifier: Development Status :: 5 - Production/Stable
Requires-Python: >=3.5
License-File: LICENSE
